pdf_tools/__init__.py
pdf_tools/server.py
mseep_mcp_pdf_tools-0.1.4.dist-info/METADATA
mseep_mcp_pdf_tools-0.1.4.dist-info/WHEEL
mseep_mcp_pdf_tools-0.1.4.dist-info/entry_points.txt
mseep_mcp_pdf_tools-0.1.4.dist-info/licenses/LICENSE
mseep_mcp_pdf_tools-0.1.4.dist-info/RECORD
