Metadata-Version: 2.4
Name: mseep-mcp-pdf-tools
Version: 0.1.4
Summary: MCP server for PDF manipulation
Project-URL: Homepage, https://github.com/hanweg/mcp-pdf-tools
Project-URL: Repository, https://github.com/hanweg/mcp-pdf-tools.git
Author-email: mseep <support@skydeck.ai>
License-Expression: MIT
License-File: LICENSE
Requires-Python: >=3.10
Requires-Dist: mcp
Requires-Dist: pypdf2
